{"stat.flyOneCm":46313,"stat.pickup.minecraft.sand":1,"stat.drop.minecraft.cooked_porkchop":15,"stat.walkOneCm":46192,"stat.drop":7,"stat.jump":343,"stat.swimOneCm":11206,"stat.mineBlock.minecraft.sand":1,"stat.useItem.minecraft.sand":1,"stat.playOneMinute":21513,"stat.fallOneCm":12892,"stat.climbOneCm":16,"stat.leaveGame":2,"stat.sneakTime":3226,"stat.pickup.minecraft.cooked_porkchop":27,"stat.damageTaken":345,"stat.damageDealt":78,"stat.crouchOneCm":13218,"stat.timeSinceDeath":21513,"stat.useItem.minecraft.cooked_porkchop":5,"stat.sprintOneCm":21277,"achievement.exploreAllBiomes":{"value":0,"progress":["ForestHills","Beach","DesertHills","Ice Plains","Ocean","River","Forest","Plains","Desert","Extreme Hills","Ice Mountains"]},"stat.diveOneCm":8301}